didigo/__init__.py
didigo/cli.py
didigo/command_type.py
didigo/constant/__init__.py
didigo/constant/version.py
didigo/utils/__init__.py
didigo/utils/file.py
didigo/version/__init__.py
didicli-0.0.10.dist-info/METADATA
didicli-0.0.10.dist-info/WHEEL
didicli-0.0.10.dist-info/entry_points.txt
didicli-0.0.10.dist-info/top_level.txt
didicli-0.0.10.dist-info/RECORD
