Metadata-Version: 2.1
Name: didicli
Version: 0.0.10
Summary: didicli
Home-page: https://github.com/xxx/xxxx
Author: didicli contributors
Author-email: myname@example.com
License: Apache License 2.0
Keywords: didicli,ll
Platform: UNKNOWN
Classifier: Development Status :: 3 - Alpha
